AUTHORS.rst
CHANGELOG.rst
LICENSE
MANIFEST.in
README.rst
setup.py
panya/__init__.py
panya/admin.py
panya/context_processors.py
panya/managers.py
panya/models.py
panya/pagemenus.py
panya/tests.py
panya/urls.py
panya/views.py
panya.egg-info/PKG-INFO
panya.egg-info/SOURCES.txt
panya.egg-info/dependency_links.txt
panya.egg-info/not-zip-safe
panya.egg-info/requires.txt
panya.egg-info/top_level.txt
panya/fixtures/photosizes.json
panya/generic/__init__.py
panya/generic/__init__.pyc
panya/generic/views.py
panya/generic/views.pyc
panya/templates/panya/modelbase_detail.html
panya/templates/panya/modelbase_list.html
panya/templates/panya/modelbase_peek.html
panya/templates/panya/inclusion_tags/content_list_gizmo.html
panya/templates/panya/inclusion_tags/modelbase_block.html
panya/templates/panya/inclusion_tags/modelbase_list.html
panya/templates/panya/inclusion_tags/modelbase_list_gizmo.html
panya/templates/panya/inclusion_tags/modelbase_list_gizmo_featured.html
panya/templates/panya/inclusion_tags/modelbase_list_wide.html
panya/templates/panya/inclusion_tags/object_comments.html
panya/templates/panya/inclusion_tags/object_header.html
panya/templates/panya/inclusion_tags/pager.html
panya/templates/panya/inclusion_tags/testmodel_block.html
panya/templates/panya/inclusion_tags/view_modifier.html
panya/templatetags/__init__.py
panya/templatetags/__init__.pyc
panya/templatetags/panya_inclusion_tags.py
panya/templatetags/panya_template_tags.py
panya/utils/__init__.py
panya/utils/__init__.pyc
panya/utils/tests.py
panya/view_modifiers/__init__.py
panya/view_modifiers/__init__.pyc
panya/view_modifiers/items.py
panya/view_modifiers/items.pyc